setup.cfg
setup.py
bin/coreec2
coreec2.egg-info/PKG-INFO
coreec2.egg-info/SOURCES.txt
coreec2.egg-info/dependency_links.txt
coreec2.egg-info/requires.txt
coreec2.egg-info/top_level.txt
lib/__init__.py
lib/cli.py
lib/cloud_config.py
lib/cluster.py
lib/cluster_conf.py
lib/cluster_launcher.py
lib/coreos.py
lib/env.py
lib/security_group.py
lib/utils.py