Metadata-Version: 1.1
Name: coreec2
Version: 0.1.4
Summary: Command line interface for CoreOS EC2 cluster formation
Home-page: http://github.com/petrjanda/coreos-ec2/
Author: Petr Janda
Author-email: UNKNOWN
License: Apache License 2.0
Platform: UNKNOWN
Classifier: Development Status :: 5 - Production/Stable
Classifier: Intended Audience :: Developers
Classifier: Intended Audience :: System Administrators
Classifier: Natural Language :: English
Classifier: License :: OSI Approved :: Apache Software License
Classifier: Programming Language :: Python
Classifier: Programming Language :: Python :: 3
Classifier: Programming Language :: Python :: 3.3
Classifier: Programming Language :: Python :: 3.4
